{
  "project_info": {
    "project_number": "849763543984",
    "project_id": "wholemart-1470437007087"
  },
  "client": [
    {
      "client_info": {
        "mobilesdk_app_id": "1:849763543984:android:5cfd8b37c1c3ad91",
        "android_client_info": {
          "package_name": "abominable.com.wholeseller"
        }
      },
      "oauth_client": [
        {
          "client_id": "849763543984-h1lj6df6n8t4ahg58hagslo8228vguqe.apps.googleusercontent.com",
          "client_type": 1,
          "android_info": {
            "package_name": "abominable.com.wholeseller",
            "certificate_hash": "6d6b5c67059995879f7bcfbd91b9b4b9ba1593cc"
          }
        },
        {
          "client_id": "849763543984-s8g14u63hmnl6ctog2kvv43dc4hv585h.apps.googleusercontent.com",
          "client_type": 3
        }
      ],
      "api_key": [
        {
          "current_key": "AIzaSyCB_GHvNzPI4EBo0GGunL-6NlUmQAxrukk"
        }
      ],
      "services": {
        "analytics_service": {
          "status": 1
        },
        "appinvite_service": {
          "status": 1,
          "other_platform_oauth_client": []
        },
        "ads_service": {
          "status": 1
        }
      }
    }
  ],
  "configuration_version": "1"
}